monte_carlo_sensitivity/__init__.py
monte_carlo_sensitivity/divide_absolute_by_unperturbed.py
monte_carlo_sensitivity/divide_by_std.py
monte_carlo_sensitivity/divide_by_unperturbed.py
monte_carlo_sensitivity/joint_perturbed_run.py
monte_carlo_sensitivity/monte_carlo_sensitivity.py
monte_carlo_sensitivity/perturbed_run.py
monte_carlo_sensitivity/repeat_rows.py
monte_carlo_sensitivity/sensitivity_analysis.py
monte_carlo_sensitivity/sensitivity_magnitude_barchart.py
monte_carlo_sensitivity/version.txt
monte_carlo_sensitivity-1.9.1.dist-info/licenses/LICENSE
monte_carlo_sensitivity-1.9.1.dist-info/METADATA
monte_carlo_sensitivity-1.9.1.dist-info/WHEEL
monte_carlo_sensitivity-1.9.1.dist-info/top_level.txt
monte_carlo_sensitivity-1.9.1.dist-info/RECORD
