Metadata-Version: 2.4
Name: monte-carlo-sensitivity
Version: 1.9.1
Summary: Monte Carlo Sensitivity Analysis
Author-email: Gregory Halverson <gregory.h.halverson@jpl.nasa.gov>, Margaret Johnson <maggie.johnson@jpl.nasa.gov>
Project-URL: Homepage, https://github.com/JPL-Evapotranspiration-Algorithms/monte-carlo-sensitivity
Classifier: Programming Language :: Python :: 3
Classifier: Operating System :: OS Independent
Requires-Python: >=3.10
License-File: LICENSE
Requires-Dist: matplotlib
Requires-Dist: numpy
Requires-Dist: pandas
Requires-Dist: scipy
Requires-Dist: seaborn
Provides-Extra: dev
Requires-Dist: build; extra == "dev"
Requires-Dist: pytest>=6.0; extra == "dev"
Requires-Dist: pytest-cov; extra == "dev"
Requires-Dist: jupyter; extra == "dev"
Requires-Dist: pytest; extra == "dev"
Requires-Dist: twine; extra == "dev"
Dynamic: license-file
